[
    {
        "mode": "train",
        "player_x": 322.0598378893939,
        "player_y": 295.6592725344492,
        "enemy_x": 675,
        "enemy_y": 353,
        "action_dx": -0.9870580689288714,
        "action_dy": -0.16036323943599856,
        "collision": false,
        "dist": 357.5677796683301,
        "missile_collision": false,
        "missile_x": 351.47988914722254,
        "missile_y": 320.74824055615204,
        "missile_angle": 0.020125560626790183,
        "missile_action": 0.05235987755982989
    },
    {
        "mode": "train",
        "player_x": 320.36754609030294,
        "player_y": 295.04596309645774,
        "enemy_x": 673.0258838621422,
        "enemy_y": 352.679273521128,
        "action_dx": -0.9869077516278943,
        "action_dy": -0.16128573953321035,
        "collision": false,
        "dist": 357.3366783168264,
        "missile_collision": false,
        "missile_x": 355.8898320439038,
        "missile_y": 320.85776245093507,
        "missile_angle": 0.024830114224086135,
        "missile_action": 0.035939408240821216
    },
    {
        "mode": "train",
        "player_x": 318.07355054042404,
        "player_y": 294.21458808051375,
        "enemy_x": 671.0520683588865,
        "enemy_y": 352.35670204206156,
        "action_dx": -0.9867038592430046,
        "action_dy": -0.1625284410648209,
        "collision": false,
        "dist": 357.73501290373605,
        "missile_collision": false,
        "missile_x": 360.8251531985316,
        "missile_y": 321.0918804340595,
        "missile_angle": 0.047401699162462764,
        "missile_action": 0.05235987755982989
    },
    {
        "mode": "train",
        "player_x": 315.2981919899148,
        "player_y": 293.20876060220775,
        "enemy_x": 669.0786606404005,
        "enemy_y": 352.03164515993194,
        "action_dx": -0.9864573910642975,
        "action_dy": -0.16401772957403002,
        "collision": false,
        "dist": 358.63735408661574,
        "missile_collision": false,
        "missile_x": 365.7211709356304,
        "missile_y": 321.13090382085915,
        "missile_angle": 0.007970265340052352,
        "missile_action": -0.011124135172163374
    },
    {
        "mode": "train",
        "player_x": 312.13774303890136,
        "player_y": 292.06337115401215,
        "enemy_x": 667.1057458582719,
        "enemy_y": 351.7036097007839,
        "action_dx": -0.9861773175682569,
        "action_dy": -0.16569338645183582,
        "collision": false,
        "dist": 359.94338593657824,
        "missile_collision": false,
        "missile_x": 370.5629312088725,
        "missile_y": 321.0808780405688,
        "missile_angle": -0.010331779650944894,
        "missile_action": 0.008401515845157914
    },
    {
        "mode": "train",
        "player_x": 308.6692217674845,
        "player_y": 290.80633212990483,
        "enemy_x": 665.1333912231354,
        "enemy_y": 351.3722229278802,
        "action_dx": -0.9858709306450918,
        "action_dy": -0.16750674048819866,
        "collision": false,
        "dist": 361.57285743520526,
        "missile_collision": false,
        "missile_x": 374.9915379412536,
        "missile_y": 321.1551934832065,
        "missile_angle": 0.01677919777123209,
        "missile_action": 0.05235987755982989
    },
    {
        "mode": "train",
        "player_x": 304.9542426397449,
        "player_y": 289.45997344506816,
        "enemy_x": 663.1616493618452,
        "enemy_y": 351.03720944690383,
        "action_dx": -0.9855441419877244,
        "action_dy": -0.1694188424989386,
        "collision": false,
        "dist": 363.4615553592951,
        "missile_collision": false,
        "missile_x": 379.12268036352447,
        "missile_y": 321.3431414390995,
        "missile_angle": 0.04546404456669058,
        "missile_action": 0.05235987755982989
    },
    {
        "mode": "train",
        "player_x": 301.04209722694713,
        "player_y": 288.04215903164805,
        "enemy_x": 661.1905610778698,
        "enemy_y": 350.69837176190595,
        "action_dx": -0.9852017337706979,
        "action_dy": -0.17139878580436602,
        "collision": false,
        "dist": 365.5580897858488,
        "missile_collision": false,
        "missile_x": 383.65205412401144,
        "missile_y": 321.44910394346994,
        "missile_angle": 0.023390248874782894,
        "missile_action": 0.0
    },
    {
        "mode": "train",
        "player_x": 296.9722187861028,
        "player_y": 286.56718003536116,
        "enemy_x": 659.2201576103284,
        "enemy_y": 350.3555741902972,
        "action_dx": -0.9848475672309109,
        "action_dy": -0.17342222844651825,
        "collision": false,
        "dist": 367.82132674882433,
        "missile_collision": false,
        "missile_x": 388.09607209178546,
        "missile_y": 321.69512268920283,
        "missile_angle": 0.05530308066491611,
        "missile_action": 0.05235987755982989
    },
    {
        "mode": "train",
        "player_x": 292.77615392282127,
        "player_y": 285.04646937278085,
        "enemy_x": 657.2504624758666,
        "enemy_y": 350.00872973340415,
        "action_dx": -0.9844847550016793,
        "action_dy": -0.17547013184380778,
        "collision": false,
        "dist": 370.2183367506017,
        "missile_collision": false,
        "missile_x": 392.9268702518094,
        "missile_y": 321.7833508212559,
        "missile_angle": 0.018261645642620727,
        "missile_action": -0.0182447736827969
    },
    {
        "mode": "train",
        "player_x": 288.47913992158993,
        "player_y": 283.48917337716574,
        "enemy_x": 655.2814929658632,
        "enemy_y": 349.65778946971653,
        "action_dx": -0.9841158027220178,
        "action_dy": -0.17752770722565653,
        "collision": false,
        "dist": 372.7227548116952,
        "missile_collision": false,
        "missile_x": 397.5409953888593,
        "missile_y": 322.03042830059525,
        "missile_angle": 0.05349697314051817,
        "missile_action": 0.05235987755982989
    },
    {
        "mode": "train",
        "player_x": 284.10136660999876,
        "player_y": 281.90260911512286,
        "enemy_x": 653.3132613604191,
        "enemy_y": 349.3027340552652,
        "action_dx": -0.9837427248826494,
        "action_dy": -0.17958354947060157,
        "collision": false,
        "dist": 375.31346907237725,
        "missile_collision": false,
        "missile_x": 401.5761700206326,
        "missile_y": 322.3963035040814,
        "missile_angle": 0.09042420598891399,
        "missile_action": 0.05235987755982989
    },
    {
        "mode": "train",
        "player_x": 279.65898585011973,
        "player_y": 280.29263023993775,
        "enemy_x": 651.3457759106539,
        "enemy_y": 348.943566956324,
        "action_dx": -0.9833671392437907,
        "action_dy": -0.18162893342054073,
        "collision": false,
        "dist": 377.9735718506531,
        "missile_collision": false,
        "missile_x": 406.1347017645729,
        "missile_y": 322.77597892592973,
        "missile_angle": 0.08309717613018963,
        "missile_action": 0.006294784538847437
    },
    {
        "mode": "train",
        "player_x": 275.16491913161036,
        "player_y": 278.66391967423885,
        "enemy_x": 649.3790416321663,
        "enemy_y": 348.5803090894829,
        "action_dx": -0.9829903435450991,
        "action_dy": -0.18365724733069524,
        "collision": false,
        "dist": 380.6895204595539,
        "missile_collision": false,
        "missile_x": 410.92270893705773,
        "missile_y": 322.90715887168466,
        "missile_angle": 0.02739075638711195,
        "missile_action": -0.04370912471549343
    },
    {
        "mode": "train",
        "player_x": 270.6295036461968,
        "player_y": 277.0202237561289,
        "enemy_x": 647.413060945076,
        "enemy_y": 348.2129945948215,
        "action_dx": -0.9826133776603788,
        "action_dy": -0.18566353988562737,
        "collision": false,
        "dist": 383.4504657325225,
        "missile_collision": false,
        "missile_x": 415.72166353693973,
        "missile_y": 322.98938709385146,
        "missile_angle": 0.01713293481119493,
        "missile_action": 0.0
    },
    {
        "mode": "train",
        "player_x": 266.0610091472598,
        "player_y": 275.36453955609016,
        "enemy_x": 645.4478341897553,
        "enemy_y": 347.84166751505023,
        "action_dx": -0.9822370738426587,
        "action_dy": -0.1876441599651091,
        "collision": false,
        "dist": 386.24771467674026,
        "missile_collision": false,
        "missile_x": 420.09714963609423,
        "missile_y": 323.2565632152699,
        "missile_angle": 0.06098632114623613,
        "missile_action": 0.05235987755982989
    },
    {
        "mode": "train",
        "player_x": 261.4660514375041,
        "player_y": 273.69926473050833,
        "enemy_x": 643.48336004207,
        "enemy_y": 347.46637919512,
        "action_dx": -0.9818620972624114,
        "action_dy": -0.18959647137924027,
        "collision": false,
        "dist": 389.07430042333976,
        "missile_collision": false,
        "missile_x": 424.488701188024,
        "missile_y": 323.72648781758784,
        "missile_angle": 0.1066008703890038,
        "missile_action": 0.05235987755982989
    },
    {
        "mode": "train",
        "player_x": 256.84992315909346,
        "player_y": 272.0263174044921,
        "enemy_x": 641.5196358475451,
        "enemy_y": 347.0871862523615,
        "action_dx": -0.9814889786609439,
        "action_dy": -0.1915186277287334,
        "collision": false,
        "dist": 391.9246380262576,
        "missile_collision": false,
        "missile_x": 428.7553763846998,
        "missile_y": 324.1068339741168,
        "missile_angle": 0.08890844392515453,
        "missile_action": -0.012716057902908251
    },
    {
        "mode": "train",
        "player_x": 252.21685842575886,
        "player_y": 270.3472320781283,
        "enemy_x": 639.5566578902233,
        "enemy_y": 346.70414899690405,
        "action_dx": -0.9811181406176501,
        "action_dy": -0.1934093951982814,
        "collision": false,
        "dist": 394.7942489582546,
        "missile_collision": false,
        "missile_x": 433.57342450455957,
        "missile_y": 324.77630513462094,
        "missile_angle": 0.1380666648080674,
        "missile_action": 0.05235987755982989
    },
    {
        "mode": "train",
        "player_x": 247.57024452848506,
        "player_y": 268.66323635148643,
        "enemy_x": 637.594421608988,
        "enemy_y": 346.3173302065075,
        "action_dx": -0.9807499186579298,
        "action_dy": -0.19526801338791755,
        "collision": false,
        "dist": 397.67954058483815,
        "missile_collision": false,
        "missile_x": 438.1790783737649,
        "missile_y": 325.1808888370946,
        "missile_angle": 0.08762008960208577,
        "missile_action": -0.04902333117168005
    },
    {
        "mode": "train",
        "player_x": 242.91279130005992,
        "player_y": 266.97531230462215,
        "enemy_x": 635.6329217716722,
        "enemy_y": 345.92679417973164,
        "action_dx": -0.9803845782018703,
        "action_dy": -0.1970940862226488,
        "collision": false,
        "dist": 400.57762963989376,
        "missile_collision": false,
        "missile_x": 442.9677374172847,
        "missile_y": 325.857360578101,
        "missile_angle": 0.14033678088184492,
        "missile_action": 0.05235987755982989
    },
    {
        "mode": "train",
        "player_x": 238.24666660671372,
        "player_y": 265.28424560157987,
        "enemy_x": 633.6721526152684,
        "enemy_y": 345.53260600728635,
        "action_dx": -0.9800223281660486,
        "action_dy": -0.19888749658034738,
        "collision": false,
        "dist": 403.4862009200635,
        "missile_collision": false,
        "missile_x": 447.80898589265405,
        "missile_y": 326.4040609068017,
        "missile_angle": 0.1124491091089604,
        "missile_action": -0.030024130810118108
    },
    {
        "mode": "train",
        "player_x": 233.57360474143064,
        "player_y": 263.5906647735953,
        "enemy_x": 631.7121079589363,
        "enemy_y": 345.13483101412567,
        "action_dx": -0.9796633318762976,
        "action_dy": -0.20064833958204378,
        "collision": false,
        "dist": 406.4033941690682,
        "missile_collision": false,
        "missile_x": 452.0797574081491,
        "missile_y": 326.818132006665,
        "missile_angle": 0.09665254082756376,
        "missile_action": -0.01971020312719736
    },
    {
        "mode": "train",
        "player_x": 228.89499313859807,
        "player_y": 261.8950726456568,
        "enemy_x": 629.7527812951837,
        "enemy_y": 344.7335343349616,
        "action_dx": -0.9793077158227262,
        "action_dy": -0.20237687054126083,
        "collision": false,
        "dist": 409.32771352650985,
        "missile_collision": false,
        "missile_x": 456.8512741409995,
        "missile_y": 327.5622247583915,
        "missile_angle": 0.1546987053156905,
        "missile_action": 0.05235987755982989
    },
    {
        "mode": "train",
        "player_x": 224.2119417457259,
        "player_y": 260.1978714777552,
        "enemy_x": 627.7941658635383,
        "enemy_y": 344.32878059387906,
        "action_dx": -0.9789555766851161,
        "action_dy": -0.2040734644119899,
        "collision": false,
        "dist": 412.2579550385725,
        "missile_collision": false,
        "missile_x": 461.6089952885499,
        "missile_y": 328.48033906069566,
        "missile_angle": 0.19063031194633143,
        "missile_action": 0.028479240334328984
    },
    {
        "mode": "train",
        "player_x": 219.5253385208221,
        "player_y": 258.4993830778831,
        "enemy_x": 625.8362547101681,
        "enemy_y": 343.9206336650551,
        "action_dx": -0.9786069869729952,
        "action_dy": -0.20573858424621255,
        "collision": false,
        "dist": 415.19314862663884,
        "missile_collision": false,
        "missile_x": 466.1286562399279,
        "missile_y": 329.1517749392892,
        "missile_angle": 0.1474802659452635,
        "missile_action": -0.05235987755982989
    },
    {
        "mode": "train",
        "player_x": 214.83589383029292,
        "player_y": 256.79986489243464,
        "enemy_x": 623.8790407362221,
        "enemy_y": 343.5091564965627,
        "action_dx": -0.9782619995568334,
        "action_dy": -0.20737275670411995,
        "collision": false,
        "dist": 418.1325116290233,
        "missile_collision": false,
        "missile_x": 470.53683706254964,
        "missile_y": 329.6655527485421,
        "missile_angle": 0.116027495387272,
        "missile_action": -0.042409421839501166
    },
    {
        "mode": "train",
        "player_x": 210.1441759672635,
        "player_y": 255.09952287852505,
        "enemy_x": 621.9225167371085,
        "enemy_y": 343.09441098315443,
        "action_dx": -0.9779206513119946,
        "action_dy": -0.20897655308078056,
        "collision": false,
        "dist": 421.0754116066537,
        "missile_collision": false,
        "missile_x": 474.6199640785914,
        "missile_y": 330.37227921974534,
        "missile_angle": 0.17138659545259718,
        "missile_action": 0.04266829372984891
    },
    {
        "mode": "train",
        "player_x": 205.45063956623383,
        "player_y": 253.39852180184656,
        "enemy_x": 619.9666754344845,
        "enemy_y": 342.67645787699286,
        "action_dx": -0.9775829660529406,
        "action_dy": -0.21055057464451446,
        "collision": false,
        "dist": 424.02133656428987,
        "missile_collision": false,
        "missile_x": 478.65861186904175,
        "missile_y": 331.00768801533803,
        "missile_angle": 0.15605284395372052,
        "missile_action": -0.029744043729406353
    },
    {
        "mode": "train",
        "player_x": 200.75564833480402,
        "player_y": 251.69699347495296,
        "enemy_x": 618.0115095023787,
        "enemy_y": 342.2553567277038,
        "action_dx": -0.9772489568996813,
        "action_dy": -0.21209544134300704,
        "collision": false,
        "dist": 426.96987110768305,
        "missile_collision": false,
        "missile_x": 483.34576753270204,
        "missile_y": 331.8132786327237,
        "missile_angle": 0.17020896974481053,
        "missile_action": -0.0019569956413620776
    },
    {
        "mode": "train",
        "player_x": 196.05949323905406,
        "player_y": 249.99504334788728,
        "enemy_x": 616.0570115885793,
        "enemy_y": 341.83116584501784,
        "action_dx": -0.9769186281899823,
        "action_dy": -0.21361178313801668,
        "collision": false,
        "dist": 429.9206773523085,
        "missile_collision": false,
        "missile_x": 488.20261583903493,
        "missile_y": 332.47616338572755,
        "missile_angle": 0.1356464178452888,
        "missile_action": -0.05235987755982989
    },
    {
        "mode": "train",
        "player_x": 191.36240705184798,
        "player_y": 248.2927557806839,
        "enemy_x": 614.1031743321993,
        "enemy_y": 341.4039422787418,
        "action_dx": -0.976591977028009,
        "action_dy": -0.21510023339021472,
        "collision": false,
        "dist": 432.87347963562775,
        "missile_collision": false,
        "missile_x": 492.83325052893554,
        "missile_y": 333.17104394641535,
        "missile_angle": 0.1489502148178414,
        "missile_action": -0.006157161189005847
    },
    {
        "mode": "train",
        "player_x": 186.66457599147702,
        "player_y": 246.5901982613704,
        "enemy_x": 612.1499903781432,
        "enemy_y": 340.97374181196136,
        "action_dx": -0.9762689945418115,
        "action_dy": -0.21656142384164484,
        "collision": false,
        "dist": 435.82805227401246,
        "missile_collision": false,
        "missile_x": 497.779974560743,
        "missile_y": 333.75593899089665,
        "missile_angle": 0.11769243322030028,
        "missile_action": -0.05235987755982989
    },
    {
        "mode": "train",
        "player_x": 181.96614903257415,
        "player_y": 244.8874247803688,
        "enemy_x": 610.1974523890597,
        "enemy_y": 340.54061896427805,
        "action_dx": -0.9759496669074488,
        "action_dy": -0.21799598084194077,
        "collision": false,
        "dist": 438.7842097568906,
        "missile_collision": false,
        "missile_x": 502.4941279434693,
        "missile_y": 334.2261153752814,
        "missile_angle": 0.09940843208436582,
        "missile_action": -0.041002843225888055
    },
    {
        "mode": "train",
        "player_x": 177.26724535484576,
        "player_y": 243.1844785300167,
        "enemy_x": 608.2455530552447,
        "enemy_y": 340.10462700259416,
        "action_dx": -0.975633976185874,
        "action_dy": -0.21940452254167706,
        "collision": false,
        "dist": 441.7417988918937,
        "missile_collision": false,
        "missile_x": 506.7338060586577,
        "missile_y": 334.52916437171564,
        "missile_angle": 0.0713578822906015,
        "missile_action": -0.05235987755982989
    },
    {
        "mode": "train",
        "player_x": 172.56796030205695,
        "player_y": 241.4813940641842,
        "enemy_x": 606.294285102873,
        "enemy_y": 339.6658179575108,
        "action_dx": -0.975321901009392,
        "action_dy": -0.2207876568366668,
        "collision": false,
        "dist": 444.70069251181457,
        "missile_collision": false,
        "missile_x": 511.32769002687326,
        "missile_y": 334.8943219912715,
        "missile_angle": 0.07932099835742232,
        "missile_action": -0.01790859849947392
    },
    {
        "mode": "train",
        "player_x": 167.86837014921977,
        "player_y": 239.7781990259674,
        "enemy_x": 604.3436413008542,
        "enemy_y": 339.22424264383744,
        "action_dx": -0.9750134171470646,
        "action_dy": -0.2221459798943123,
        "collision": false,
        "dist": 447.6607844318509,
        "missile_collision": false,
        "missile_x": 515.545469992999,
        "missile_y": 335.123849111362,
        "missile_angle": 0.054365317343075405,
        "missile_action": -0.05235987755982989
    },
    {
        "mode": "train",
        "player_x": 163.16853591634393,
        "player_y": 238.07491552984317,
        "enemy_x": 602.39361446656,
        "enemy_y": 338.7799506840488,
        "action_dx": -0.9747084979725198,
        "action_dy": -0.22348007513009818,
        "collision": false,
        "dist": 450.6219854077843,
        "missile_collision": false,
        "missile_x": 520.1299583929521,
        "missile_y": 335.53245506034244,
        "missile_angle": 0.0888930414169797,
        "missile_action": 0.005622721748789444
    },
    {
        "mode": "train",
        "player_x": 160.35941494131606,
        "player_y": 236.4023189578819,
        "enemy_x": 600.444197470615,
        "enemy_y": 338.3329905337886,
        "action_dx": -0.9742101402045464,
        "action_dy": -0.2256426438478284,
        "collision": false,
        "dist": 451.73496391332793,
        "missile_collision": false,
        "missile_x": 524.431462340546,
        "missile_y": 335.8206797888019,
        "missile_angle": 0.06690556099798428,
        "missile_action": -0.05235987755982989
    },
    {
        "mode": "train",
        "player_x": 159.06286457256655,
        "player_y": 234.75427192525103,
        "enemy_x": 598.4957771902059,
        "enemy_y": 337.8817052460929,
        "action_dx": -0.9735496508820154,
        "action_dy": -0.22847555069964456,
        "collision": false,
        "dist": 451.3718557851902,
        "missile_collision": false,
        "missile_x": 528.4333650304047,
        "missile_y": 336.00630239921895,
        "missile_angle": 0.04635036828579397,
        "missile_action": -0.05235987755982989
    },
    {
        "mode": "train",
        "player_x": 158.97637068883975,
        "player_y": 233.12586452408448,
        "enemy_x": 596.5486778884418,
        "enemy_y": 337.4247541446936,
        "action_dx": -0.9727485771990486,
        "action_dy": -0.23186247121349007,
        "collision": false,
        "dist": 449.8308375423754,
        "missile_collision": false,
        "missile_x": 533.0835830539071,
        "missile_y": 336.13277625560266,
        "missile_angle": 0.027190700606400532,
        "missile_action": -0.05235987755982989
    },
    {
        "mode": "train",
        "player_x": 159.8579219931311,
        "player_y": 231.5131688280894,
        "enemy_x": 594.6031807340437,
        "enemy_y": 336.9610292022666,
        "action_dx": -0.9718219120164178,
        "action_dy": -0.23571629414351883,
        "collision": false,
        "dist": 447.35074746243026,
        "missile_collision": false,
        "missile_x": 537.2079859128696,
        "missile_y": 336.17564072356566,
        "missile_angle": 0.010392516500908288,
        "missile_action": -0.051355543273181016
    },
    {
        "mode": "train",
        "player_x": 161.513909447837,
        "player_y": 229.91304249623147,
        "enemy_x": 592.6595369100108,
        "enemy_y": 336.4895966139796,
        "action_dx": -0.9707800862680063,
        "action_dy": -0.23997088178669176,
        "collision": false,
        "dist": 444.12285909122585,
        "missile_collision": false,
        "missile_x": 541.6406236459148,
        "missile_y": 336.14863322721135,
        "missile_angle": -0.006092797062973103,
        "missile_action": -0.05235987755982989
    },
    {
        "mode": "train",
        "player_x": 163.78944582287448,
        "player_y": 228.32297165568326,
        "enemy_x": 590.7179767374748,
        "enemy_y": 336.0096548504062,
        "action_dx": -0.9696302478098947,
        "action_dy": -0.2445755149889748,
        "collision": false,
        "dist": 440.30034322764214,
        "missile_collision": false,
        "missile_x": 545.7391985922202,
        "missile_y": 336.06161293139456,
        "missile_angle": -0.0212286525195095,
        "missile_action": -0.05235987755982989
    },
    {
        "mode": "train",
        "player_x": 166.56062133417728,
        "player_y": 226.74094520818284,
        "enemy_x": 588.778716241855,
        "enemy_y": 335.52050382042825,
        "action_dx": -0.9683771052807899,
        "action_dy": -0.24949104586737766,
        "collision": false,
        "dist": 436.00586239102756,
        "missile_collision": false,
        "missile_x": 550.1549067446877,
        "missile_y": 335.9064063247295,
        "missile_angle": -0.03513428260774021,
        "missile_action": -0.05235987755982989
    },
    {
        "mode": "train",
        "player_x": 169.7283081544923,
        "player_y": 225.16535427512065,
        "enemy_x": 586.8419620312934,
        "enemy_y": 335.0215217286935,
        "action_dx": -0.9670234983214132,
        "action_dy": -0.2546871682951768,
        "collision": false,
        "dist": 431.3376609780825,
        "missile_collision": false,
        "missile_x": 554.4704103437087,
        "missile_y": 336.14565293376336,
        "missile_angle": 0.055382170122308595,
        "missile_action": 0.050876428718069855
    },
    {
        "mode": "train",
        "player_x": 173.21320402201712,
        "player_y": 223.59491175360904,
        "enemy_x": 584.9079150346506,
        "enemy_y": 334.51214739210315,
        "action_dx": -0.9655707907322902,
        "action_dy": -0.2601404391566596,
        "collision": false,
        "dist": 426.3744460418108,
        "missile_collision": false,
        "missile_x": 559.4299568306025,
        "missile_y": 336.36303138760974,
        "missile_angle": 0.0438022736612754,
        "missile_action": -0.05235987755982989
    },
    {
        "mode": "train",
        "player_x": 176.95186712730978,
        "player_y": 222.0285879613379,
        "enemy_x": 582.9767734531861,
        "enemy_y": 333.99186651378983,
        "action_dx": -0.9640191460660131,
        "action_dy": -0.26583281591661095,
        "collision": false,
        "dist": 421.1792970946584,
        "missile_collision": false,
        "missile_x": 563.4768639876078,
        "missile_y": 336.71060129015143,
        "missile_angle": 0.08567507472987769,
        "missile_action": 0.0
    },
    {
        "mode": "train",
        "player_x": 180.8935440228167,
        "player_y": 220.46555915245912,
        "enemy_x": 581.0487351610541,
        "enemy_y": 333.4602008819566,
        "action_dx": -0.9623677232434392,
        "action_dy": -0.27175055705414686,
        "collision": false,
        "dist": 415.8027970738734,
        "missile_collision": false,
        "missile_x": 567.8170258424448,
        "missile_y": 337.0421047357439,
        "missile_angle": 0.07623241791325167,
        "missile_action": -0.05235987755982989
    },
    {
        "mode": "train",
        "player_x": 184.99763195049505,
        "player_y": 218.90516633029424,
        "enemy_x": 579.1239997145672,
        "enemy_y": 332.91669976784834,
        "action_dx": -0.9606148164802962,
        "action_dy": -0.2778833826599331,
        "collision": false,
        "dist": 410.2855390136035,
        "missile_collision": true,
        "missile_x": 572.7610142654114,
        "missile_y": 337.6386856061942,
        "missile_angle": 0.1200873265323414,
        "missile_action": 0.0
    },
    {
        "mode": "train",
        "player_x": 189.2316487039105,
        "player_y": 217.34688229750049,
        "enemy_x": 577.2027700816066,
        "enemy_y": 332.3609330025285,
        "action_dx": -0.958757955532363,
        "action_dy": -0.2842238250101558,
        "collision": false,
        "dist": 404.6601325589731,
        "missile_collision": false
    },
    {
        "mode": "train",
        "player_x": 193.56960851791567,
        "player_y": 215.79028529620362,
        "enemy_x": 575.2852541705419,
        "enemy_y": 331.7924853525082,
        "action_dx": -0.956793977002369,
        "action_dy": -0.2907667201933369,
        "collision": false,
        "dist": 398.95280993358625,
        "missile_collision": false
    },
    {
        "mode": "train",
        "player_x": 197.9907227803926,
        "player_y": 214.23503792010428,
        "enemy_x": 573.3716662165372,
        "enemy_y": 331.2109519121215,
        "action_dx": -0.9547190740369048,
        "action_dy": -0.29750880603793056,
        "collision": false,
        "dist": 393.1847112354164,
        "missile_collision": false
    },
    {
        "mode": "train",
        "player_x": 202.47836060164693,
        "player_y": 212.68087024416295,
        "enemy_x": 571.4622280684633,
        "enemy_y": 330.61593430004564,
        "action_dx": -0.9525288294869935,
        "action_dy": -0.304448401204766,
        "collision": false,
        "dist": 387.3729130755457,
        "missile_collision": false
    },
    {
        "mode": "train",
        "player_x": 207.0192172699232,
        "player_y": 211.12756632834802,
        "enemy_x": 569.5571704094893,
        "enemy_y": 330.00703749763613,
        "action_dx": -0.950218236092781,
        "action_dy": -0.3115851469449788,
        "collision": false,
        "dist": 381.53125184198984,
        "missile_collision": false
    },
    {
        "mode": "train",
        "player_x": 211.602649015817,
        "player_y": 209.57495342063422,
        "enemy_x": 567.6567339373038,
        "enemy_y": 329.38386720374615,
        "action_dx": -0.9477817062216513,
        "action_dy": -0.3189197976789396,
        "collision": false,
        "dist": 375.67098265791896,
        "missile_collision": false
    },
    {
        "mode": "train",
        "player_x": 216.22014082380485,
        "player_y": 208.02289331940133,
        "enemy_x": 565.7611705248605,
        "enemy_y": 328.74602760838826,
        "action_dx": -0.9452130729763343,
        "action_dy": -0.326454049867106,
        "collision": false,
        "dist": 369.80130691633724,
        "missile_collision": false
    },
    {
        "mode": "train",
        "player_x": 220.86488068146792,
        "player_y": 206.47127546335315,
        "enemy_x": 563.8707443789078,
        "enemy_y": 328.09311950865407,
        "action_dx": -0.9425055839904258,
        "action_dy": -0.33419040103938724,
        "collision": false,
        "dist": 363.9297947129449,
        "missile_collision": false
    },
    {
        "mode": "train",
        "player_x": 225.5314189788712,
        "player_y": 204.92001140345275,
        "enemy_x": 561.9857332109269,
        "enemy_y": 327.4247387065753,
        "action_dx": -0.9396518888750508,
        "action_dy": -0.3421320326037145,
        "collision": false,
        "dist": 358.0627232440921,
        "missile_collision": false
    },
    {
        "mode": "train",
        "player_x": 230.21539602806658,
        "player_y": 203.36903038047058,
        "enemy_x": 560.1064294331768,
        "enemy_y": 326.7404746413679,
        "action_dx": -0.9366440210274836,
        "action_dy": -0.3502827113539391,
        "collision": false,
        "dist": 352.20534802883276,
        "missile_collision": false
    },
    {
        "mode": "train",
        "player_x": 234.9133240786957,
        "player_y": 201.81827578702297,
        "enemy_x": 558.2331413911219,
        "enemy_y": 326.03990921866,
        "action_dx": -0.9334733743307447,
        "action_dy": -0.35864670556910666,
        "collision": false,
        "dist": 346.36212044530015,
        "missile_collision": false
    },
    {
        "mode": "train",
        "player_x": 239.6224129304718,
        "player_y": 200.26770233720305,
        "enemy_x": 556.3661946424604,
        "enemy_y": 325.3226158075218,
        "action_dx": -0.9301306751428645,
        "action_dy": -0.3672287123282696,
        "collision": false,
        "dist": 340.5368623751044,
        "missile_collision": false
    },
    {
        "mode": "train",
        "player_x": 244.34043042316546,
        "player_y": 198.71727380228523,
        "enemy_x": 554.5059332921746,
        "enemy_y": 324.5881583828653,
        "action_dx": -0.9266059498825464,
        "action_dy": -0.3760337932184603,
        "collision": false,
        "dist": 334.7329065913345,
        "missile_collision": false
    },
    {
        "mode": "train",
        "player_x": 249.0655908285932,
        "player_y": 197.16696119928915,
        "enemy_x": 552.6527213924095,
        "enemy_y": 323.8360907964284,
        "action_dx": -0.9228884884558275,
        "action_dy": -0.3850673160315193,
        "collision": false,
        "dist": 328.95320979870144,
        "missile_collision": false
    },
    {
        "mode": "train",
        "player_x": 253.79646556420818,
        "player_y": 195.61674134183042,
        "enemy_x": 550.8069444154978,
        "enemy_y": 323.06595616436533,
        "action_dx": -0.9189668037305648,
        "action_dy": -0.3943349003591106,
        "collision": false,
        "dist": 323.2004438523453,
        "missile_collision": false
    },
    {
        "mode": "train",
        "player_x": 258.53191176397297,
        "player_y": 194.06659568080158,
        "enemy_x": 548.9690108080367,
        "enemy_y": 322.27728636364714,
        "action_dx": -0.9148285872489581,
        "action_dy": -0.4038423652269228,
        "collision": false,
        "dist": 317.47706957590435,
        "missile_collision": false
    },
    {
        "mode": "train",
        "player_x": 263.2710151350576,
        "player_y": 192.51650937691664,
        "enemy_x": 547.1393536335388,
        "enemy_y": 321.4696016331933,
        "action_dx": -0.9104606613712759,
        "action_dy": -0.4135956770753036,
        "collision": false,
        "dist": 311.78539671438125,
        "missile_collision": false
    },
    {
        "mode": "train",
        "player_x": 268.0130442431981,
        "player_y": 190.96647055874683,
        "enemy_x": 545.3184323107962,
        "enemy_y": 320.6424102790427,
        "action_dx": -0.9058489280661691,
        "action_dy": -0.4236008965068091,
        "collision": false,
        "dist": 306.127632848887,
        "missile_collision": false
    },
    {
        "mode": "train",
        "player_x": 272.7574139409833,
        "player_y": 189.41646972914913,
        "enemy_x": 543.5067344546638,
        "enemy_y": 319.7952084860291,
        "action_dx": -0.9009783146051644,
        "action_dy": -0.4338641222908821,
        "collision": false,
        "dist": 300.50592353305524,
        "missile_collision": false
    },
    {
        "mode": "train",
        "player_x": 277.50365611048426,
        "player_y": 187.8664992904091,
        "enemy_x": 541.7047778254536,
        "enemy_y": 318.9274802414473,
        "action_dx": -0.8958327164826998,
        "action_dy": -0.44439143114964186,
        "collision": false,
        "dist": 294.92238545640515,
        "missile_collision": false
    },
    {
        "mode": "train",
        "player_x": 282.25139625735784,
        "player_y": 186.31655316435524,
        "enemy_x": 539.9131123924882,
        "enemy_y": 318.038697379148,
        "action_dx": -0.8903949379707929,
        "action_dy": -0.4551888118528265,
        "collision": false,
        "dist": 289.3791340754256,
        "missile_collision": false
    },
    {
        "mode": "train",
        "player_x": 287.0003347861295,
        "player_y": 184.7666264884503,
        "enemy_x": 538.1323225165467,
        "enemy_y": 317.12831975544236,
        "action_dx": -0.8846466308322071,
        "action_dy": -0.4662620921297641,
        "collision": false,
        "dist": 283.87830686041457,
        "missile_collision": false
    },
    {
        "mode": "train",
        "player_x": 291.7502320204196,
        "player_y": 183.21671537266448,
        "enemy_x": 536.3630292548822,
        "enemy_y": 316.1957955711828,
        "action_dx": -0.878568231861587,
        "action_dy": -0.47761685686709654,
        "collision": false,
        "dist": 278.42208307049265,
        "missile_collision": false
    },
    {
        "mode": "train",
        "player_x": 296.5008962191245,
        "player_y": 181.66681670497397,
        "enemy_x": 534.605892791159,
        "enemy_y": 315.24056185744865,
        "action_dx": -0.8721389001048868,
        "action_dy": -0.48925835600819173,
        "collision": false,
        "dist": 273.0127007789689,
        "missile_collision": false
    },
    {
        "mode": "train",
        "player_x": 301.2521739893612,
        "player_y": 180.1169279957597,
        "enemy_x": 532.8616149909492,
        "enemy_y": 314.2620451454323,
        "action_dx": -0.8653364548284924,
        "action_dy": -0.5011914005096821,
        "collision": false,
        "dist": 267.65247171690277,
        "missile_collision": false
    },
    {
        "mode": "train",
        "player_x": 306.0039426168234,
        "player_y": 178.56704725332645,
        "enemy_x": 531.1309420812922,
        "enemy_y": 313.25966234441296,
        "action_dx": -0.8581373155761821,
        "action_dy": -0.5134202446492578,
        "collision": false,
        "dist": 262.3437943766739,
        "missile_collision": false
    },
    {
        "mode": "train",
        "player_x": 310.75610393006593,
        "player_y": 177.01717288431797,
        "enemy_x": 529.4146674501399,
        "enemy_y": 312.2328218551144,
        "action_dx": -0.850516445970187,
        "action_dy": -0.5259484529250387,
        "collision": false,
        "dist": 257.0891657134852,
        "missile_collision": false
    },
    {
        "mode": "train",
        "player_x": 315.50857939193276,
        "player_y": 175.46730361404934,
        "enemy_x": 527.7136345581995,
        "enemy_y": 311.18092494926435,
        "action_dx": -0.8424473032878484,
        "action_dy": -0.538778749750797,
        "collision": false,
        "dist": 251.89119169601074,
        "missile_collision": false
    },
    {
        "mode": "train",
        "player_x": 320.261306172699,
        "player_y": 173.9174384227726,
        "enemy_x": 526.0287399516238,
        "enemy_y": 310.10336744976274,
        "action_dx": -0.8339017962830525,
        "action_dy": -0.5519128501456533,
        "collision": false,
        "dist": 246.75259688381928,
        "missile_collision": false
    },
    {
        "mode": "train",
        "player_x": 325.0142340085848,
        "player_y": 172.36757649468933,
        "enemy_x": 524.3609363590577,
        "enemy_y": 308.99954174947146,
        "action_dx": -0.8248502542261469,
        "action_dy": -0.5653512696572467,
        "collision": false,
        "dist": 241.67623314548752,
        "missile_collision": false
    },
    {
        "mode": "train",
        "player_x": 329.76732268856625,
        "player_y": 170.81771717716086,
        "enemy_x": 522.7112358506055,
        "enemy_y": 307.868839210157,
        "action_dx": -0.8152614107100381,
        "action_dy": -0.5790931118629185,
        "collision": false,
        "dist": 236.6650875747915,
        "missile_collision": false
    },
    {
        "mode": "train",
        "player_x": 334.5205400438242,
        "player_y": 169.26785994807622,
        "enemy_x": 521.0807130291854,
        "enemy_y": 306.7106529864311,
        "action_dx": -0.8051024064134561,
        "action_dy": -0.5931358319872964,
        "collision": false,
        "dist": 231.72228961088734,
        "missile_collision": false
    },
    {
        "mode": "train",
        "player_x": 339.2738603393034,
        "player_y": 167.71800438974665,
        "enemy_x": 519.4705082163584,
        "enemy_y": 305.5243813224565,
        "action_dx": -0.7943388157205554,
        "action_dy": -0.607474975484312,
        "collision": false,
        "dist": 226.85111732025365,
        "missile_collision": false
    },
    {
        "mode": "train",
        "player_x": 344.0272629869595,
        "player_y": 166.16815016802116,
        "enemy_x": 517.8818305849173,
        "enemy_y": 304.3094313714879,
        "action_dx": -0.7829347028587098,
        "action_dy": -0.62210389088925,
        "collision": false,
        "dist": 222.05500275203926,
        "missile_collision": false
    },
    {
        "mode": "train",
        "player_x": 348.7807315163572,
        "player_y": 164.6182970155789,
        "enemy_x": 516.3159611791999,
        "enemy_y": 303.0652235897094,
        "action_dx": -0.7708527140149701,
        "action_dy": -0.6370134168883373,
        "collision": false,
        "dist": 217.33753623339925,
        "missile_collision": false
    },
    {
        "mode": "train",
        "player_x": 353.2518919970636,
        "player_y": 162.63459958837976,
        "enemy_x": 514.77425575117,
        "enemy_y": 301.7911967559327,
        "action_dx": -0.7576113151170333,
        "action_dy": -0.6527059791411745,
        "collision": false,
        "dist": 213.19951343276202,
        "missile_collision": false
    },
    {
        "mode": "train",
        "player_x": 357.49720603881684,
        "player_y": 160.30382674137513,
        "enemy_x": 513.2590331209359,
        "enemy_y": 300.48578479765035,
        "action_dx": -0.7433028932309977,
        "action_dy": -0.6689550126237399,
        "collision": false,
        "dist": 209.55364024624163,
        "missile_collision": false
    },
    {
        "mode": "train",
        "player_x": 361.56184292940765,
        "player_y": 157.69539355852612,
        "enemy_x": 511.7724273344739,
        "enemy_y": 299.1478747724029,
        "action_dx": -0.7280117453848861,
        "action_dy": -0.6855646567477437,
        "collision": false,
        "dist": 206.32989145752413,
        "missile_collision": false
    },
    {
        "mode": "train",
        "player_x": 365.4819380990685,
        "player_y": 154.8648321070016,
        "enemy_x": 510.3164038437041,
        "enemy_y": 297.7767454589074,
        "action_dx": -0.7118153656168011,
        "action_dy": -0.7023666316617125,
        "collision": false,
        "dist": 203.47195739324044,
        "missile_collision": false
    },
    {
        "mode": "train",
        "player_x": 369.28639989198535,
        "player_y": 151.85656804053667,
        "enemy_x": 508.8927731124705,
        "enemy_y": 296.372012195584,
        "action_dx": -0.6947856551537354,
        "action_dy": -0.7192168611709508,
        "collision": false,
        "dist": 200.9344496175506,
        "missile_collision": false
    },
    {
        "mode": "train",
        "player_x": 372.99835498350706,
        "player_y": 148.70614188211943,
        "enemy_x": 507.503201802163,
        "enemy_y": 294.93357847324205,
        "action_dx": -0.6769900288273888,
        "action_dy": -0.7359921880484135,
        "collision": false,
        "dist": 198.6806911345964,
        "missile_collision": false
    },
    {
        "mode": "train",
        "player_x": 376.63630471391264,
        "player_y": 145.44198605014032,
        "enemy_x": 506.1492217445082,
        "enemy_y": 293.4615940971452,
        "action_dx": -0.6584923980494292,
        "action_dy": -0.7525873781237048,
        "collision": false,
        "dist": 196.6809600448475,
        "missile_collision": false
    },
    {
        "mode": "train",
        "player_x": 380.2150501554253,
        "player_y": 142.0868464793117,
        "enemy_x": 504.8322369484094,
        "enemy_y": 291.9564193408978,
        "action_dx": -0.6393540165131376,
        "action_dy": -0.7689125057953724,
        "collision": false,
        "dist": 194.91108771414662,
        "missile_collision": false
    },
    {
        "mode": "train",
        "player_x": 383.7464321658236,
        "player_y": 138.6589199174035,
        "enemy_x": 503.55352891538314,
        "enemy_y": 290.41859432930704,
        "action_dx": -0.6196341804821646,
        "action_dy": -0.7848907455042364,
        "collision": false,
        "dist": 193.35133619699994,
        "missile_collision": false
    },
    {
        "mode": "train",
        "player_x": 387.23992343133045,
        "player_y": 135.1727637626316,
        "enemy_x": 502.3142605544188,
        "enemy_y": 288.84881283829856,
        "action_dx": -0.5993907811737443,
        "action_dy": -0.8004565518776946,
        "collision": false,
        "dist": 191.9854971705545,
        "missile_collision": false
    },
    {
        "mode": "train",
        "player_x": 390.7031021009241,
        "player_y": 131.64002393356878,
        "enemy_x": 501.1154789920713,
        "enemy_y": 287.2478997345432,
        "action_dx": -0.5786807120809755,
        "action_dy": -0.8155541879393761,
        "collision": false,
        "dist": 190.80016766775705,
        "missile_collision": false
    },
    {
        "mode": "train",
        "player_x": 394.14203069378726,
        "player_y": 128.0700171650732,
        "enemy_x": 499.95811756790937,
        "enemy_y": 285.61679135866444,
        "action_dx": -0.557560138816388,
        "action_dy": -0.8301365499741896,
        "collision": false,
        "dist": 189.784167675173,
        "missile_collision": false
    },
    {
        "mode": "train",
        "player_x": 397.56155922526597,
        "player_y": 124.47019684503144,
        "enemy_x": 498.84299729027657,
        "enemy_y": 283.9565182587161,
        "action_dx": -0.5360846429937358,
        "action_dy": -0.8441642349367088,
        "collision": false,
        "dist": 188.9280720660265,
        "missile_collision": false
    },
    {
        "mode": "train",
        "player_x": 400.96556770763715,
        "player_y": 120.8465256837527,
        "enemy_x": 497.7708280042891,
        "enemy_y": 282.2681897888427,
        "action_dx": -0.5143092546949141,
        "action_dy": -0.8576047985728403,
        "collision": false,
        "dist": 188.2238350038566,
        "missile_collision": false
    },
    {
        "mode": "train",
        "player_x": 402.69072753071686,
        "player_y": 118.01005682666461,
        "enemy_x": 496.74220949489927,
        "enemy_y": 280.552980191697,
        "action_dx": -0.5008276074008055,
        "action_dy": -0.8655470568751215,
        "collision": false,
        "dist": 187.79212761910367,
        "missile_collision": false
    },
    {
        "mode": "train",
        "player_x": 403.07280842636334,
        "player_y": 115.80334981292904,
        "enemy_x": 495.7405542800977,
        "enemy_y": 278.8218860779467,
        "action_dx": -0.49418507631292363,
        "action_dy": -0.8693567221512639,
        "collision": false,
        "dist": 187.51627739372702,
        "missile_collision": false
    },
    {
        "mode": "train",
        "player_x": 402.3804261800633,
        "player_y": 114.10045227387548,
        "enemy_x": 494.7521841274718,
        "enemy_y": 277.0831726336442,
        "action_dx": -0.49307270550109805,
        "action_dy": -0.8699881074416059,
        "collision": false,
        "dist": 187.339021034501,
        "missile_collision": false
    },
    {
        "mode": "train",
        "player_x": 400.828473420206,
        "player_y": 112.80060231456753,
        "enemy_x": 493.7660387164696,
        "enemy_y": 275.343196418761,
        "action_dx": -0.4963647211937357,
        "action_dy": -0.8681140844118732,
        "collision": false,
        "dist": 187.23644394539716,
        "missile_collision": false
    },
    {
        "mode": "train",
        "player_x": 398.58886424950293,
        "player_y": 111.82319041905606,
        "enemy_x": 492.7733092740821,
        "enemy_y": 273.60696824993727,
        "action_dx": -0.5031158587628703,
        "action_dy": -0.8642189726344242,
        "collision": false,
        "dist": 187.2022982065656,
        "missile_collision": false
    },
    {
        "mode": "train",
        "player_x": 395.79912995012324,
        "player_y": 111.10372897458178,
        "enemy_x": 491.7670775565564,
        "enemy_y": 271.8785303046684,
        "action_dx": -0.5125429473602399,
        "action_dy": -0.8586615905648035,
        "collision": false,
        "dist": 187.23884135114682,
        "missile_collision": false
    },
    {
        "mode": "train",
        "player_x": 392.5692955478022,
        "player_y": 110.59062789093726,
        "enemy_x": 490.7419916618359,
        "enemy_y": 270.1612071235388,
        "action_dx": -0.5240022490308162,
        "action_dy": -0.851716879608856,
        "collision": false,
        "dist": 187.3516693785417,
        "missile_collision": false
    },
    {
        "mode": "train",
        "player_x": 388.9873810631281,
        "player_y": 110.24261509595654,
        "enemy_x": 489.6939871637743,
        "enemy_y": 268.4577733643211,
        "action_dx": -0.5369674550443214,
        "action_dy": -0.8436029588753376,
        "collision": false,
        "dist": 187.54694563813712,
        "missile_collision": false
    },
    {
        "mode": "train",
        "player_x": 385.1238025125716,
        "player_y": 110.02667293190686,
        "enemy_x": 488.6200522536856,
        "enemy_y": 266.7705674465704,
        "action_dx": -0.5510101169412871,
        "action_dy": -0.8344985626280905,
        "collision": false,
        "dist": 187.83003534605166,
        "missile_collision": false
    },
    {
        "mode": "train",
        "player_x": 381.0348927093092,
        "player_y": 109.91638727260201,
        "enemy_x": 487.51803201980306,
        "enemy_y": 265.1015703213142,
        "action_dx": -0.5657829091864264,
        "action_dy": -0.8245542430140931,
        "collision": false,
        "dist": 188.2049414741291,
        "missile_collision": false
    },
    {
        "mode": "train",
        "player_x": 376.765717903882,
        "player_y": 109.89062681709302,
        "enemy_x": 258,
        "enemy_y": 251,
        "action_dx": 0.64393514620679,
        "action_dy": -0.7650800791287407,
        "collision": false,
        "dist": 184.43739032337606,
        "missile_collision": false
    },
    {
        "mode": "train",
        "player_x": 372.35233109672293,
        "player_y": 109.93248652462073,
        "enemy_x": 259.2878702924136,
        "enemy_y": 249.46983984174253,
        "action_dx": 0.6295535452033696,
        "action_dy": -0.7769570990227639,
        "collision": false,
        "dist": 179.59466937444577,
        "missile_collision": false
    },
    {
        "mode": "train",
        "player_x": 367.87375024048873,
        "player_y": 110.28462737652713,
        "enemy_x": 260.54697738282033,
        "enemy_y": 247.915925643697,
        "action_dx": 0.6149404578485135,
        "action_dy": -0.788573543368696,
        "collision": false,
        "dist": 174.53197539347403,
        "missile_collision": false
    },
    {
        "mode": "train",
        "player_x": 363.3430141449944,
        "player_y": 110.88499314393648,
        "enemy_x": 261.77685829851737,
        "enemy_y": 246.3387785569596,
        "action_dx": 0.5999085784359022,
        "action_dy": -0.8000685580117588,
        "collision": false,
        "dist": 169.30272294369095,
        "missile_collision": false
    },
    {
        "mode": "train",
        "player_x": 358.770553858092,
        "player_y": 111.6839388437482,
        "enemy_x": 262.97667545538917,
        "enemy_y": 244.73864144093608,
        "action_dx": 0.5842826022760276,
        "action_dy": -0.8115502699633298,
        "collision": false,
        "dist": 163.95127636788294,
        "missile_collision": false
    },
    {
        "mode": "train",
        "player_x": 354.1647142180631,
        "player_y": 112.6417484894818,
        "enemy_x": 264.14524065994124,
        "enemy_y": 243.1155409010094,
        "action_dx": 0.5678934685093852,
        "action_dy": -0.823102064402939,
        "collision": false,
        "dist": 158.5147189567196,
        "missile_collision": false
    },
    {
        "mode": "train",
        "player_x": 349.53217109553304,
        "player_y": 113.72664929195291,
        "enemy_x": 265.28102759696003,
        "enemy_y": 241.46933677220352,
        "action_dx": 0.5505734718008958,
        "action_dy": -0.8347867105728913,
        "collision": false,
        "dist": 153.02434246058408,
        "missile_collision": false
    },
    {
        "mode": "train",
        "player_x": 344.878265187002,
        "player_y": 114.91322301981403,
        "enemy_x": 266.38217454056183,
        "enemy_y": 239.79976335105775,
        "action_dx": 0.5321520082955447,
        "action_dy": -0.8466488292480056,
        "collision": false,
        "dist": 147.5068954411336,
        "missile_collision": false
    },
    {
        "mode": "train",
        "player_x": 340.20726904967023,
        "player_y": 116.18113508798716,
        "enemy_x": 267.44647855715294,
        "enemy_y": 238.10646569256173,
        "action_dx": 0.5124517949057629,
        "action_dy": -0.8587159937359162,
        "collision": false,
        "dist": 141.98562911834,
        "missile_collision": false
    },
    {
        "mode": "train",
        "player_x": 335.52260072929784,
        "player_y": 117.5141178284099,
        "enemy_x": 268.47138214696446,
        "enemy_y": 236.3890337050899,
        "action_dx": 0.4912854673677453,
        "action_dy": -0.8709986162751672,
        "collision": false,
        "dist": 136.4811764972137,
        "missile_collision": false
    },
    {
        "mode": "train",
        "player_x": 330.82699466249295,
        "player_y": 118.89915710663232,
        "enemy_x": 269.4539530816999,
        "enemy_y": 234.64703647253955,
        "action_dx": 0.4684525289809272,
        "action_dy": -0.8834886689094397,
        "collision": false,
        "dist": 131.01229640984988,
        "missile_collision": false
    },
    {
        "mode": "train",
        "player_x": 326.1226383985421,
        "player_y": 120.32584161509449,
        "enemy_x": 270.39085813966176,
        "enemy_y": 232.88005913472068,
        "action_dx": 0.4437366966371496,
        "action_dy": -0.8961572094546527,
        "collision": false,
        "dist": 125.59650955452327,
        "missile_collision": false,
        "missile_x": 355.2623681402344,
        "missile_y": 145.4841861497345,
        "missile_angle": 0.038231331441432946,
        "missile_action": 0.05235987755982989
    },
    {
        "mode": "train",
        "player_x": 321.4112819768745,
        "player_y": 121.78584230774845,
        "enemy_x": 271.2783315329361,
        "enemy_y": 231.08774471581137,
        "action_dx": 0.41690378265422207,
        "action_dy": -0.9089506235261633,
        "collision": false,
        "dist": 120.25064902209922,
        "missile_collision": false,
        "missile_x": 359.6230463380268,
        "missile_y": 145.8116618102689,
        "missile_angle": 0.07495671716554274,
        "missile_action": 0.05235987755982989
    },
    {
        "mode": "train",
        "player_x": 316.6943254290334,
        "player_y": 123.27249594775586,
        "enemy_x": 272.11213909824454,
        "enemy_y": 229.26984346875903,
        "action_dx": 0.3877003700946653,
        "action_dy": -0.921785453903705,
        "collision": false,
        "dist": 114.99134323731286,
        "missile_collision": false,
        "missile_x": 363.9334949632943,
        "missile_y": 146.28769990363497,
        "missile_angle": 0.10999244575271226,
        "missile_action": 0.05235987755982989
    },
    {
        "mode": "train",
        "player_x": 311.9728887802536,
        "player_y": 124.78047194564601,
        "enemy_x": 272.8875398384339,
        "enemy_y": 227.42627256095162,
        "action_dx": 0.3558536963331221,
        "action_dy": -0.9345416774045201,
        "collision": false,
        "dist": 109.83544457897403,
        "missile_collision": false,
        "missile_x": 368.41966163068685,
        "missile_y": 146.92905189491987,
        "missile_angle": 0.14199995119077796,
        "missile_action": 0.05235987755982989
    },
    {
        "mode": "train",
        "player_x": 307.2478680507228,
        "player_y": 126.30550582984237,
        "enemy_x": 273.59924723110015,
        "enemy_y": 225.55718920614257,
        "action_dx": 0.3210733641882322,
        "action_dy": -0.9470543251624222,
        "collision": false,
        "dist": 104.8004119080268,
        "missile_collision": false,
        "missile_x": 373.14788368990634,
        "missile_y": 147.74446377426509,
        "missile_angle": 0.17077653152406275,
        "missile_action": 0.05235987755982989
    }
]